ftl_sdk/__init__.py
ftl_sdk/ftl.py
ftl_sdk/py.typed
ftl_sdk/response.py
ftl_sdk/validation.py
ftl_sdk-0.1.0.dist-info/METADATA
ftl_sdk-0.1.0.dist-info/WHEEL
ftl_sdk-0.1.0.dist-info/top_level.txt
ftl_sdk-0.1.0.dist-info/RECORD
