Metadata-Version: 2.4
Name: ftl-sdk
Version: 0.1.0
Summary: Python SDK for building MCP tools that compile to WebAssembly
Author-email: FTL CLI Contributors <ftl-cli@fastertools.com>
Maintainer-email: FTL CLI Contributors <ftl-cli@fastertools.com>
License: Apache-2.0
Project-URL: Homepage, https://github.com/fastertools/ftl-cli
Project-URL: Repository, https://github.com/fastertools/ftl-cli
Project-URL: Issues, https://github.com/fastertools/ftl-cli/issues
Project-URL: Documentation, https://github.com/fastertools/ftl-cli/tree/main/sdk/python
Keywords: ftl,mcp,wasm,webassembly,spin,fermyon,model-context-protocol
Classifier: Development Status :: 3 - Alpha
Classifier: Intended Audience :: Developers
Classifier: License :: OSI Approved :: Apache Software License
Classifier: Operating System :: OS Independent
Classifier: Programming Language :: Python :: 3
Classifier: Programming Language :: Python :: 3.10
Classifier: Programming Language :: Python :: 3.11
Classifier: Programming Language :: Python :: 3.12
Classifier: Programming Language :: Python :: 3.13
Classifier: Topic :: Software Development :: Libraries :: Python Modules
Classifier: Topic :: Internet :: WWW/HTTP :: HTTP Servers
Classifier: Typing :: Typed
Requires-Python: >=3.10
Requires-Dist: spin-sdk>=3.3.0
Requires-Dist: typing_extensions>=4.0.0; python_version < "3.11"
Provides-Extra: dev
Requires-Dist: pytest>=7.0; extra == "dev"
Requires-Dist: pytest-cov>=4.0; extra == "dev"
Requires-Dist: black>=23.0; extra == "dev"
Requires-Dist: ruff>=0.1.0; extra == "dev"
Requires-Dist: mypy>=1.0; extra == "dev"
Requires-Dist: types-requests; extra == "dev"
